ConglingkaishiXueReactjsReactjs101/README.md
ConglingkaishiXueReactjsReactjs101/__init__.py
ConglingkaishiXueReactjsReactjs101/__main__.py
ConglingkaishiXueReactjsReactjs101/file.epub
ConglingkaishiXueReactjsReactjs101/index.html
ConglingkaishiXueReactjsReactjs101/css/__init__.py
ConglingkaishiXueReactjsReactjs101/css/annotations.css
ConglingkaishiXueReactjsReactjs101/css/main.css
ConglingkaishiXueReactjsReactjs101/css/normalize.css
ConglingkaishiXueReactjsReactjs101/css/popup.css
ConglingkaishiXueReactjsReactjs101/font/__init__.py
ConglingkaishiXueReactjsReactjs101/font/fontello.eot
ConglingkaishiXueReactjsReactjs101/font/fontello.svg
ConglingkaishiXueReactjsReactjs101/font/fontello.ttf
ConglingkaishiXueReactjsReactjs101/font/fontello.woff
ConglingkaishiXueReactjsReactjs101/img/__init__.py
ConglingkaishiXueReactjsReactjs101/img/annotator-glyph-sprite.png
ConglingkaishiXueReactjsReactjs101/img/annotator-icon-sprite.png
ConglingkaishiXueReactjsReactjs101/img/apple-touch-icon.png
ConglingkaishiXueReactjsReactjs101/img/cancelfullscreen.png
ConglingkaishiXueReactjsReactjs101/img/close.png
ConglingkaishiXueReactjsReactjs101/img/fullscreen.png
ConglingkaishiXueReactjsReactjs101/img/loader.gif
ConglingkaishiXueReactjsReactjs101/img/menu-icon.png
ConglingkaishiXueReactjsReactjs101/img/save.png
ConglingkaishiXueReactjsReactjs101/img/saved.png
ConglingkaishiXueReactjsReactjs101/img/settings-s.png
ConglingkaishiXueReactjsReactjs101/img/settings.png
ConglingkaishiXueReactjsReactjs101/img/star.png
ConglingkaishiXueReactjsReactjs101/js/__init__.py
ConglingkaishiXueReactjsReactjs101/js/epub.js
ConglingkaishiXueReactjsReactjs101/js/epub.min.js
ConglingkaishiXueReactjsReactjs101/js/epub.min.map
ConglingkaishiXueReactjsReactjs101/js/hooks.min.js
ConglingkaishiXueReactjsReactjs101/js/hooks.min.map
ConglingkaishiXueReactjsReactjs101/js/reader.js
ConglingkaishiXueReactjsReactjs101/js/reader.js.map
ConglingkaishiXueReactjsReactjs101/js/reader.min.js
conglingkaishi_xue_reactjs_reactjs_101-2024.3.2.0.dist-info/METADATA
conglingkaishi_xue_reactjs_reactjs_101-2024.3.2.0.dist-info/WHEEL
conglingkaishi_xue_reactjs_reactjs_101-2024.3.2.0.dist-info/entry_points.txt
conglingkaishi_xue_reactjs_reactjs_101-2024.3.2.0.dist-info/top_level.txt
conglingkaishi_xue_reactjs_reactjs_101-2024.3.2.0.dist-info/RECORD
